{
  "id": "org.zotero.Zotero",
  "runtime": "org.freedesktop.Platform",
  "runtime-version": "22.08",
  "sdk": "org.freedesktop.Sdk",
  "command": "zotero",
  "rename-desktop-file": "zotero.desktop",
  "rename-icon": "zotero",
  "finish-args": [
    "--socket=x11",
    "--share=ipc",
    "--share=network",
    "--filesystem=home",
    "--filesystem=xdg-desktop",
    "--filesystem=xdg-documents",
    "--filesystem=xdg-download",
    "--filesystem=xdg-music",
    "--filesystem=xdg-pictures",
    "--filesystem=xdg-public-share",
    "--filesystem=xdg-videos"
  ],
  "modules": [
    "shared-modules/dbus-glib/dbus-glib.json",
    {
      "name": "zotero",
      "buildsystem": "simple",
      "sources": [
        {
          "type": "archive",
          "url": "https://download.zotero.org/client/release/6.0.20/Zotero-6.0.20_linux-x86_64.tar.bz2",
          "sha512": "c054d3bf344bb8ca5a762ef99d5e214158de02f70f248ca28a9a345273edfa9e93525e0cd70e2c2eeb7039714e310e6b24d04268eb608087cab738b849200b4b",
          "only-arches": [
            "x86_64"
          ]
        },
        {
          "type": "archive",
          "url": "https://download.zotero.org/client/release/6.0.20/Zotero-6.0.20_linux-i686.tar.bz2",
          "sha512": "9ac5b251db998e0ba8a838441111c9e4c994feee40608bf2a7e6dc1b6d50a7585d6d9a9ffa4ba0aa1afbde94b2cfc4a32522d4bf79255cef729634354ebd76ab",
          "only-arches": [
            "i386"
          ]
        },
        {
          "type": "file",
          "path": "org.zotero.Zotero.appdata.xml"
        }
      ],
      "build-commands": [
        "mkdir -p /app/{bin,share}",
        "cp -R . /app/share/zotero",
        "install -D chrome/icons/default/default16.png /app/share/icons/hicolor/16x16/apps/zotero.png",
        "install -D chrome/icons/default/default32.png /app/share/icons/hicolor/32x32/apps/zotero.png",
        "install -D chrome/icons/default/default48.png /app/share/icons/hicolor/48x48/apps/zotero.png",
        "install -D chrome/icons/default/default256.png /app/share/icons/hicolor/256x256/apps/zotero.png",
        "desktop-file-install --dir=/app/share/applications --set-key=Exec --set-value='zotero -url %U' --set-key=Icon --set-value=org.zotero.Zotero --remove-key=SingleMainWindow --set-key=X-GNOME-SingleWindow --set-value=true --add-mime-type=x-scheme-handler/zotero zotero.desktop",
        "install -D org.zotero.Zotero.appdata.xml /app/share/appdata/org.zotero.Zotero.appdata.xml",
        "ln -s /app/share/zotero/zotero /app/bin/zotero",
        "sed -i 's/pref(\"app.update.enabled\", true);/pref(\"app.update.enabled\", false);/' /app/share/zotero/defaults/preferences/prefs.js"
      ]
    }
  ]
}
